{
  "Blur": [
    {
      "kategory": "blur"
    },
    {
      "label": "Blur Type",
      "type": "radio",
      "options": [
        "Box",
        "Gaussian"
      ],
      "default": "Box"
    },
    {
      "label": "Blur Kernel",
      "type": "slider",
      "min": 1.0,
      "max": 64.0,
      "default": 8.0,
      "integer": true
    }
  ],
  "Invert": [
    {
      "kategory": "invert"
    },
    {
      "label": "Invert type",
      "type": "radio",
      "options": [
        "Luminance",
        "R",
        "G",
        "B",
        "RG",
        "GB",
        "RB"
      ],
      "default": "Luminance"
    },
    {
      "label": "Impact Factor",
      "type": "slider",
      "min": 0.0,
      "max": 100.0,
      "default": 100.0
    }
  ],
  "Mix Screen": [
    {
      "kategory": "mix",
      "num_inputs": 2
    }
  ],
  "Cristalline Growth": [
    {
      "kategory": "cristalline_growth"
    },
    {
      "label": "Cluster Seeds (%)",
      "type": "slider",
      "min": 1.0,
      "max": 100.0,
      "default": 30.0
    }
  ],
  "Subtract Images": [
    {
      "kategory": "subtract_images",
      "num_inputs": 2
    }
  ],
  "Contrast Mask": [
    {
      "kategory": "contrast_mask"
    },
    {
      "label": "Luminance Range",
      "type": "dualslider",
      "min": 0,
      "max": 255,
      "default": [
        50,
        200
      ]
    }
  ],
  "Scale to fit": [
    {
      "kategory": "scale_to_fit",
      "num_inputs": 2
    },
    {
      "label": "Downscale [%]",
      "type": "slider",
      "min": 0.0,
      "max": 100.0,
      "default": 0.0,
      "integer": false
    }
  ],
  "Alpha Over": [
    {
      "kategory": "alpha_over",
      "num_inputs": 2
    }
  ],
  "Mix Percent": [
    {
      "kategory": "mix_percent",
      "num_inputs": 2
    },
    {
      "label": "%",
      "type": "slider",
      "min": 0.0,
      "max": 100.0,
      "default": 50.0,
      "integer": true
    }
  ],
  "Kuwahara": [
    {
      "kategory": "kuwahara",
      "num_inputs": 1
    },
    {
      "label": "KernelSize",
      "type": "slider",
      "min": 1.0,
      "max": 64.0,
      "default": 4.0,
      "integer": true
    },
    {
      "label": "isAnisotropic",
      "type": "switch",
      "default": false
    },
    {
      "label": "regionsCount",
      "type": "slider",
      "min": 3.0,
      "max": 16.0,
      "default": 8.0,
      "integer": true
    },
    {
      "label": "stylePapari",
      "type": "switch",
      "default": false
    }
  ],
  "Difference": [
    {
      "kategory": "difference",
      "num_inputs": 2
    }
  ],
  "Add (Clamp Maximum)": [
    {
      "kategory": "add_(clamp_maximum)",
      "num_inputs": 2
    }
  ],
  "Multiply": [
    {
      "kategory": "multiply",
      "num_inputs": 1
    },
    {
      "label": "factor",
      "type": "slider",
      "min": 0.0,
      "max": 5.0,
      "default": 1.1,
      "integer": false
    },
    {
      "label": "allowValueOverflow",
      "type": "switch",
      "default": false
    }
  ],
  "PixelSort": [
    {
      "kategory": "pixelsort",
      "num_inputs": 1
    },
    {
      "label": "vSplitting",
      "type": "switch",
      "default": true
    },
    {
      "label": "flipHorz",
      "type": "switch",
      "default": false
    },
    {
      "label": "flipVert",
      "type": "switch",
      "default": false
    }
  ]
}